LICENSE
MANIFEST.in
README.rst
setup.cfg
setup.py
versioneer.py
artellapipe/__init__.py
artellapipe/tools/__init__.py
artellapipe/tools/renamer/__init__.py
artellapipe/tools/renamer/__logging__.ini
artellapipe/tools/renamer/__version__.py
artellapipe/tools/renamer/_version.py
artellapipe/tools/renamer/core/__init__.py
artellapipe/tools/renamer/core/renamer.py
artellapipe/tools/renamer/resources/icons/color/cameras.png
artellapipe/tools/renamer/resources/icons/color/characters.png
artellapipe/tools/renamer/resources/icons/color/fx.png
artellapipe/tools/renamer/resources/icons/color/lights.png
artellapipe/tools/renamer/resources/icons/color/override_add.png
artellapipe/tools/renamer/resources/icons/color/override_delete.png
artellapipe/tools/renamer/resources/icons/color/props.png
artellapipe/tools/renamer/resources/icons/color/shading_load.png
artellapipe/tools/renamer/resources/icons/color/shading_unload.png
artellapipe/tools/renamer/resources/icons/default/cameras.png
artellapipe/tools/renamer/resources/icons/default/characters.png
artellapipe/tools/renamer/resources/icons/default/fx.png
artellapipe/tools/renamer/resources/icons/default/lights.png
artellapipe/tools/renamer/resources/icons/default/override_add.png
artellapipe/tools/renamer/resources/icons/default/override_delete.png
artellapipe/tools/renamer/resources/icons/default/props.png
artellapipe/tools/renamer/resources/icons/default/shading_load.png
artellapipe/tools/renamer/resources/icons/default/shading_unload.png
artellapipe_tools_renamer.egg-info/PKG-INFO
artellapipe_tools_renamer.egg-info/SOURCES.txt
artellapipe_tools_renamer.egg-info/dependency_links.txt
artellapipe_tools_renamer.egg-info/not-zip-safe
artellapipe_tools_renamer.egg-info/requires.txt
artellapipe_tools_renamer.egg-info/top_level.txt
tests/__init__.py
tests/test_general.py