Metadata-Version: 2.1
Name: artellapipe-tools-renamer
Version: 0.0.4
Summary: Tool to rename DCC objects in an easy way
Home-page: https://github.com/ArtellaPipe/artellapipe-tools-renamer
Author: Tomas Poveda
Author-email: tpovedatd@gmail.com
License: MIT
Platform: UNKNOWN
Provides-Extra: dev
Provides-Extra: test
